infinitum/__init__.py
infinitum/main.py
infinitum-0.0.6.dist-info/LICENSE
infinitum-0.0.6.dist-info/METADATA
infinitum-0.0.6.dist-info/WHEEL
infinitum-0.0.6.dist-info/top_level.txt
infinitum-0.0.6.dist-info/RECORD
