Metadata-Version: 2.1
Name: infinitum
Version: 0.0.6
Summary: A tool to help working with databases not suck
Author-email: Jacob Hochendoner <hochen97@gmail.com>
License: MIT License
Project-URL: Homepage, https://github.com/hochen97/infinitum
Classifier: License :: OSI Approved :: MIT License
Classifier: Programming Language :: Python
Classifier: Programming Language :: Python :: 3
Requires-Python: >=3.11
License-File: LICENSE
Requires-Dist: psycopg2-binary
